apex/__init__.py
apex/auth.py
apex/client.py
apex/database.py
apex/email.py
apex/organizations.py
apex/payments.py
apex/quickstart.py
apex/setup.py
apex/sync.py
apex/users.py
apex/api/__init__.py
apex/api/v1/__init__.py
apex/api/v1/auth/__init__.py
apex/api/v1/auth/router.py
apex/api/v1/files/__init__.py
apex/api/v1/modules/__init__.py
apex/api/v1/modules/router.py
apex/api/v1/organizations/__init__.py
apex/api/v1/organizations/router.py
apex/api/v1/payments/__init__.py
apex/api/v1/payments/router.py
apex/api/v1/permissions/__init__.py
apex/api/v1/permissions/router.py
apex/api/v1/roles/__init__.py
apex/api/v1/roles/router.py
apex/api/v1/schemas/__init__.py
apex/api/v1/schemas/auth.py
apex/api/v1/schemas/password_reset.py
apex/api/v1/schemas/user.py
apex/api/v1/settings/__init__.py
apex/api/v1/settings/router.py
apex/api/v1/users/__init__.py
apex/api/v1/users/router.py
apex/app/api/__init__.py
apex/app/api/router.py
apex/app/auth/__init__.py
apex/app/auth/routes.py
apex/app/auth/schemas.py
apex/app/auth/services.py
apex/app/auth/utils.py
apex/app/core/__init__.py
apex/app/core/auth.py
apex/app/core/config.py
apex/app/core/dependencies.py
apex/app/core/exceptions.py
apex/app/core/security.py
apex/app/core/utils.py
apex/app/custom_fields/__init__.py
apex/app/custom_fields/engine.py
apex/app/database/__init__.py
apex/app/database/base.py
apex/app/database/migrate.py
apex/app/database/session.py
apex/app/models/__init__.py
apex/app/models/associations.py
apex/app/models/base_org_location.py
apex/app/models/base_org_settings.py
apex/app/models/base_organization.py
apex/app/models/base_payment.py
apex/app/models/base_permission.py
apex/app/models/base_role.py
apex/app/models/base_user.py
apex/app/models/default.py
apex/app/modules/__init__.py
apex/app/modules/routes.py
apex/app/modules/services.py
apex/app/organizations/__init__.py
apex/app/organizations/routes.py
apex/app/organizations/schemas.py
apex/app/organizations/services.py
apex/app/payments/__init__.py
apex_saas_framework-0.3.32.dist-info/licenses/LICENSE
apex_saas_framework-0.3.32.dist-info/METADATA
apex_saas_framework-0.3.32.dist-info/WHEEL
apex_saas_framework-0.3.32.dist-info/entry_points.txt
apex_saas_framework-0.3.32.dist-info/top_level.txt
apex_saas_framework-0.3.32.dist-info/RECORD
